CHANGELOG.md
LICENSE
MANIFEST.in
README.md
TODO.md
pyproject.toml
setup.py
kycli/__init__.py
kycli/cli.py
kycli/config.py
kycli/kycli.c
kycli/kyfactory.c
kycli/tui.py
kycli.egg-info/PKG-INFO
kycli.egg-info/SOURCES.txt
kycli.egg-info/dependency_links.txt
kycli.egg-info/entry_points.txt
kycli.egg-info/requires.txt
kycli.egg-info/top_level.txt
kycli/core/audit.c
kycli/core/audit.pxd
kycli/core/audit.pyx
kycli/core/engine.c
kycli/core/engine.pxd
kycli/core/engine.pyx
kycli/core/query.c
kycli/core/query.pxd
kycli/core/query.pyx
kycli/core/security.c
kycli/core/security.pxd
kycli/core/security.pyx
kycli/core/sqlite_defs.pxd
kycli/core/storage.c
kycli/core/storage.pyx
tests/conftest.py
tests/test_cli.py
tests/test_cli_coverage.py
tests/test_cli_env.py
tests/test_cli_workspaces.py
tests/test_config.py
tests/test_final_coverage.py
tests/test_init.py
tests/test_tui.py
tests/core/test_security_ops.py
tests/core/test_storage.py
tests/core/test_storage_advanced.py
tests/core/test_storage_scaling.py
tests/integration/benchmark.py
tests/integration/test_performance.py
tests/interface/test_final.py
tests/interface/test_full_coverage.py
tests/interface/test_gap_coverage.py
tests/interface/test_new_features.py
tests/interface/verify_encryption.py