Metadata-Version: 2.4
Name: kycli
Version: 0.2.3
Summary: **kycli** is a high-performance Python CLI toolkit built with Cython for speed.
Author: Balakrishna Maduru
Author-email: balakrishnamaduru@gmail.com
Classifier: Programming Language :: Python :: 3
Classifier: Programming Language :: Cython
Classifier: Operating System :: OS Independent
Requires-Python: >=3.9
License-File: LICENSE
Requires-Dist: prompt-toolkit>=3.0.43
Requires-Dist: rich>=13.7.0
Requires-Dist: tomli>=2.0.1
Requires-Dist: cryptography>=42.0.0
Dynamic: author
Dynamic: author-email
Dynamic: classifier
Dynamic: description
Dynamic: description-content-type
Dynamic: license-file
Dynamic: requires-dist
Dynamic: requires-python
Dynamic: summary
